dataexchange/__init__.py
dataexchange/json/decoders.py
dataexchange/json/encoders.py
dataexchange/json/exchange.py
dataexchange/json/keyrename.py
dataexchange/json/nesteddict.py
dataexchange/json/__pycache__/encoders.cpython-37.pyc
dataexchange/json/__pycache__/exchange.cpython-37.pyc
dataexchange/json/__pycache__/keyrename.cpython-37.pyc
dataexchange/json/__pycache__/nesteddict.cpython-37.pyc
dataexchange-1.0.2.dist-info/License
dataexchange-1.0.2.dist-info/METADATA
dataexchange-1.0.2.dist-info/WHEEL
dataexchange-1.0.2.dist-info/top_level.txt
dataexchange-1.0.2.dist-info/RECORD
